[
  {
    "id": 1,
    "text_name": "枪",
    "bullet_prefab": "Bullet_Player_1",
    "bullet_speed": 6,
    "max_lifetime": 3,
    "rate_of_fire": 2,
    "row_count": 2,
    "row_space": 0.4,
    "column_count": 2,
    "column_space": 0.05,
    "bullet_scale": 2000,
    "level_id": 1001
  },
  {
    "id": 2,
    "text_name": "导弹",
    "bullet_prefab": "Bullet_Player_1",
    "bullet_speed": 10,
    "max_lifetime": 3,
    "rate_of_fire": 0.2,
    "row_count": 1,
    "row_space": 0,
    "column_count": 1,
    "column_space": 1,
    "bullet_scale": 10000,
    "level_id": 1002
  }
]